simple_playgrounds/__init__.py
simple_playgrounds/engine.py
simple_playgrounds/agents/__init__.py
simple_playgrounds/agents/agent.py
simple_playgrounds/agents/agents.py
simple_playgrounds/agents/parts/__init__.py
simple_playgrounds/agents/parts/actuators.py
simple_playgrounds/agents/parts/controllers.py
simple_playgrounds/agents/parts/parts.py
simple_playgrounds/agents/sensors/__init__.py
simple_playgrounds/agents/sensors/robotic_sensors.py
simple_playgrounds/agents/sensors/semantic_sensors.py
simple_playgrounds/agents/sensors/sensor.py
simple_playgrounds/agents/sensors/topdown_sensors.py
simple_playgrounds/common/__init__.py
simple_playgrounds/common/definitions.py
simple_playgrounds/common/entity.py
simple_playgrounds/common/position_utils.py
simple_playgrounds/common/texture.py
simple_playgrounds/common/timer.py
simple_playgrounds/configs/__init__.py
simple_playgrounds/configs/agent_parts.yml
simple_playgrounds/configs/agent_sensors.yml
simple_playgrounds/configs/element_activable.yml
simple_playgrounds/configs/element_basic.yml
simple_playgrounds/configs/element_conditioning.yml
simple_playgrounds/configs/element_contact.yml
simple_playgrounds/configs/element_gem.yml
simple_playgrounds/configs/element_proximity.yml
simple_playgrounds/configs/element_teleport.yml
simple_playgrounds/configs/element_zone.yml
simple_playgrounds/configs/parser.py
simple_playgrounds/configs/playground.yml
simple_playgrounds/elements/__init__.py
simple_playgrounds/elements/element.py
simple_playgrounds/elements/field.py
simple_playgrounds/elements/collection/__init__.py
simple_playgrounds/elements/collection/activable.py
simple_playgrounds/elements/collection/basic.py
simple_playgrounds/elements/collection/conditioning.py
simple_playgrounds/elements/collection/contact.py
simple_playgrounds/elements/collection/edible.py
simple_playgrounds/elements/collection/gem.py
simple_playgrounds/elements/collection/proximity.py
simple_playgrounds/elements/collection/teleport.py
simple_playgrounds-0.9.31.dist-info/LICENSE.md
simple_playgrounds-0.9.31.dist-info/METADATA
simple_playgrounds-0.9.31.dist-info/WHEEL
simple_playgrounds-0.9.31.dist-info/top_level.txt
simple_playgrounds-0.9.31.dist-info/RECORD
