Metadata-Version: 2.1
Name: simple-playgrounds
Version: 0.9.31
Summary: Simulator for Reinforcement Learning
Home-page: UNKNOWN
Author: Michael Garcia Ortiz
Author-email: michael.garcia-ortiz@city.ac.uk
License: UNKNOWN
Platform: UNKNOWN
Requires-Dist: pyyaml
Requires-Dist: pygame
Requires-Dist: pymunk
Requires-Dist: numpy
Requires-Dist: scikit-image
Requires-Dist: pillow
Requires-Dist: pytest
